mykit_learn/__init__.py
mykit_learn/__main__.py
mykit_learn/base.py
mykit_learn/cli.py
mykit_learn-0.1.2.dist-info/LICENSE
mykit_learn-0.1.2.dist-info/METADATA
mykit_learn-0.1.2.dist-info/WHEEL
mykit_learn-0.1.2.dist-info/entry_points.txt
mykit_learn-0.1.2.dist-info/top_level.txt
mykit_learn-0.1.2.dist-info/RECORD
