Metadata-Version: 2.1
Name: mykit-learn
Version: 0.1.2
Summary: Learn Python with useful examples.
Home-page: https://github.com/sbavery/mykit_learn/
Author: sbavery
License: UNKNOWN
Platform: UNKNOWN
License-File: LICENSE
Provides-Extra: test
Requires-Dist: pytest ; extra == 'test'
Requires-Dist: coverage ; extra == 'test'
Requires-Dist: flake8 ; extra == 'test'
Requires-Dist: black ; extra == 'test'
Requires-Dist: isort ; extra == 'test'
Requires-Dist: pytest-cov ; extra == 'test'
Requires-Dist: codecov ; extra == 'test'
Requires-Dist: mypy ; extra == 'test'
Requires-Dist: gitchangelog ; extra == 'test'
Requires-Dist: mkdocs ; extra == 'test'
